sma_query_sw/__init__.py
sma_query_sw/commands.py
sma_query_sw/protocol.py
sma_query_sw/settings.py
sma_query_sw/collectors/__init__.py
sma_query_sw/collectors/mqtt.py
sma_query_sw-0.0.3.dist-info/LICENSE
sma_query_sw-0.0.3.dist-info/METADATA
sma_query_sw-0.0.3.dist-info/WHEEL
sma_query_sw-0.0.3.dist-info/top_level.txt
sma_query_sw-0.0.3.dist-info/RECORD
