Metadata-Version: 2.1
Name: sma-query-sw
Version: 0.0.3
Summary: SMA Sunny Boy Inverter Query Tool
Home-page: https://github.com/wired-square/sma-query
Author: Garth Berry
Author-email: garth@wiredsquare.com
License: UNKNOWN
Platform: UNKNOWN
Classifier: Programming Language :: Python :: 3
Classifier: License :: OSI Approved :: MIT License
Classifier: Operating System :: OS Independent
Requires-Python: >=3.8
License-File: LICENSE
